setup.py
DustyShock.egg-info/PKG-INFO
DustyShock.egg-info/SOURCES.txt
DustyShock.egg-info/dependency_links.txt
DustyShock.egg-info/not-zip-safe
DustyShock.egg-info/top_level.txt
dustyshock/__init__.py