Metadata-Version: 1.1
Name: DustyShock
Version: 1.0.0
Summary: Two-fluid dusty gas shocks.
Home-page: UNKNOWN
Author: Andrew Lehmann
Author-email: andrew.lehmann.35@gmail.com
License: Apache
Keywords: Dust shocks ISM
Platform: UNKNOWN
Classifier: Development Status :: 3 - Alpha
Classifier: License :: OSI Approved :: Apache Software License
Classifier: Programming Language :: Python :: 2.7
Classifier: Topic :: Scientific/Engineering :: Astronomy
